python_pypi_package_template/__init__.py
python_pypi_package_template-0.0.4.dist-info/licenses/LICENSE.txt
python_pypi_package_template-0.0.4.dist-info/METADATA
python_pypi_package_template-0.0.4.dist-info/WHEEL
python_pypi_package_template-0.0.4.dist-info/top_level.txt
python_pypi_package_template-0.0.4.dist-info/RECORD
