Metadata-Version: 2.4
Name: python_pypi_package_template
Version: 0.0.4
Summary: Python PYPI Package Template
Home-page: https://github.com/rogervila/python_package_template
Download-URL: https://github.com/rogervila/python_package_template/archive/0.0.4.tar.gz
Author: Roger Vilà
Author-email: rogervila@me.com
License: MIT
Keywords: package template,project template,pypi template
Classifier: Development Status :: 5 - Production/Stable
Classifier: Intended Audience :: Developers
Classifier: Topic :: Software Development :: Build Tools
Classifier: License :: OSI Approved :: MIT License
Classifier: Programming Language :: Python :: 3.9
License-File: LICENSE.txt
Dynamic: author
Dynamic: author-email
Dynamic: classifier
Dynamic: description
Dynamic: description-content-type
Dynamic: download-url
Dynamic: home-page
Dynamic: keywords
Dynamic: license
Dynamic: license-file
Dynamic: summary
